aioecowitt/__init__.py
aioecowitt/__main__.py
aioecowitt/calc.py
aioecowitt/py.typed
aioecowitt/sensor.py
aioecowitt/server.py
aioecowitt/station.py
aioecowitt-2025.9.2.dist-info/licenses/LICENSE
aioecowitt-2025.9.2.dist-info/METADATA
aioecowitt-2025.9.2.dist-info/WHEEL
aioecowitt-2025.9.2.dist-info/entry_points.txt
aioecowitt-2025.9.2.dist-info/top_level.txt
aioecowitt-2025.9.2.dist-info/RECORD
