Metadata-Version: 2.4
Name: aioecowitt
Version: 2025.9.2
Summary: Python wrapper for EcoWitt Protocol
Author-email: Home Assistant Team <hello@home-assistant.io>
License-Expression: Apache-2.0
Project-URL: Source code, https://github.com/home-assistant-libs/aioecowitt
Classifier: Development Status :: 4 - Beta
Classifier: Intended Audience :: Developers
Classifier: Natural Language :: English
Classifier: Programming Language :: Python :: 3
Classifier: Programming Language :: Python :: 3.13
Classifier: Topic :: Home Automation
Requires-Python: >=3.13
License-File: LICENSE
Requires-Dist: aiohttp>3
Requires-Dist: meteocalc>=1.1.0
Dynamic: license-file
